lisatools/__init__.py
lisatools/__main__.py
lisatools/cli.py
lisatools/fund.py
lisatools/io.py
lisatools/portfolio.py
lisatools/scraping.py
lisatools-0.5.1.dist-info/METADATA
lisatools-0.5.1.dist-info/WHEEL
lisatools-0.5.1.dist-info/LICENSE
lisatools-0.5.1.dist-info/RECORD
