Metadata-Version: 2.1
Name: lisatools
Version: 0.5.1
Summary: Tools for monitoring my Lifetime ISA portfolio.
License: MIT
Author: Istvan Kleijn
Requires-Python: >=3.9,<4.0
Classifier: License :: OSI Approved :: MIT License
Classifier: Programming Language :: Python :: 3
Classifier: Programming Language :: Python :: 3.9
Classifier: Programming Language :: Python :: 3.10
Classifier: Programming Language :: Python :: 3.11
Requires-Dist: beautifulsoup4 (>=4.11.1,<5.0.0)
Requires-Dist: cachetools (>=5.2.1,<6.0.0)
Requires-Dist: requests (>=2.28.1,<3.0.0)
